erika/__init__.py
erika/__version__.py
erika/config.py
erika/downloads.py
erika/main.py
erika/frontend/__init__.py
erika/frontend/application.py
erika/frontend/details.py
erika/frontend/downloads.py
erika/frontend/episode_list.py
erika/frontend/main_window.py
erika/frontend/player.py
erika/frontend/player_widgets.py
erika/frontend/podcast_list.py
erika/frontend/preferences.py
erika/frontend/util.py
erika/frontend/data/add_podcast.glade
erika/frontend/data/episode_details_template.html
erika/frontend/data/menu.glade
erika/frontend/data/player_title.glade
erika/frontend/data/podcast_details_template.html
erika/frontend/data/preferences.glade
erika/frontend/data/icons/hicolor/16x16/apps/erika.png
erika/frontend/data/icons/hicolor/16x16/status/feed-article-read.svg
erika/frontend/data/icons/hicolor/16x16/status/feed-article-unread-symbolic.svg
erika/frontend/data/icons/hicolor/16x16/status/feed-article-unread.svg
erika/frontend/data/icons/hicolor/22x22/apps/erika.png
erika/frontend/data/icons/hicolor/24x24/apps/erika.png
erika/frontend/data/icons/hicolor/32x32/apps/erika.png
erika/frontend/data/icons/hicolor/48x48/apps/erika.png
erika/frontend/data/icons/hicolor/64x64/apps/erika.png
erika/frontend/data/icons/hicolor/96x96/apps/erika.png
erika/frontend/data/icons/hicolor/scalable/apps/erika.svg
erika/frontend/widgets/__init__.py
erika/frontend/widgets/filter_button.py
erika/frontend/widgets/indexed_listbox.py
erika/frontend/widgets/label.py
erika/frontend/widgets/listbox.py
erika/frontend/widgets/network_button.py
erika/frontend/widgets/paned.py
erika/frontend/widgets/scrolled_window.py
erika/frontend/widgets/sort_button.py
erika/frontend/widgets/status_box.py
erika/frontend/widgets/webview.py
erika/library/__init__.py
erika/library/gpodder.py
erika/library/opml.py
erika/library/fields/__init__.py
erika/library/fields/image.py
erika/library/fields/json.py
erika/library/models/__init__.py
erika/library/models/config.py
erika-0.1.1.dist-info/DESCRIPTION.rst
erika-0.1.1.dist-info/METADATA
erika-0.1.1.dist-info/RECORD
erika-0.1.1.dist-info/WHEEL
erika-0.1.1.dist-info/entry_points.txt
erika-0.1.1.dist-info/metadata.json
erika-0.1.1.dist-info/top_level.txt
