Metadata-Version: 2.0
Name: erika
Version: 0.1.1
Summary: A GTK podcast manager
Home-page: https://github.com/Muges/erika
Author: Muges
Author-email: git@muges.fr
License: MIT
Platform: UNKNOWN
Classifier: Environment :: X11 Applications :: GTK
Classifier: License :: OSI Approved :: MIT License
Classifier: Programming Language :: Python
Classifier: Programming Language :: Python :: 3 :: Only
Classifier: Topic :: Multimedia :: Sound/Audio :: Players
Requires-Dist: feedparser
Requires-Dist: lxml
Requires-Dist: mutagen
Requires-Dist: mygpoclient
Requires-Dist: peewee
Requires-Dist: pillow
Requires-Dist: requests
